lbl2vec/__init__.py
lbl2vec/_version.py
lbl2vec/lbl2transformervec.py
lbl2vec/lbl2vec.py
lbl2vec/utils.py
lbl2vec-1.0.2.data/data/requirements/requirements.txt
tests/__init__.py
tests/test_lbl2vec.py
lbl2vec-1.0.2.dist-info/LICENSE
lbl2vec-1.0.2.dist-info/METADATA
lbl2vec-1.0.2.dist-info/WHEEL
lbl2vec-1.0.2.dist-info/top_level.txt
lbl2vec-1.0.2.dist-info/RECORD
