Metadata-Version: 2.1
Name: lbl2vec
Version: 1.0.2
Summary: Lbl2Vec learns jointly embedded label, document and word vectors to retrieve documents with predefined topics from an unlabeled document corpus.
Home-page: https://github.com/sebischair/Lbl2Vec
Author: Tim Schopf
Author-email: tim.schopf@tum.de
License: BSD 3-Clause "New" or "Revised" License
Classifier: Development Status :: 3 - Alpha
Classifier: Programming Language :: Python :: 3
Classifier: Intended Audience :: Science/Research
Classifier: Intended Audience :: Developers
Classifier: Topic :: Scientific/Engineering :: Artificial Intelligence
Classifier: Topic :: Scientific/Engineering :: Information Analysis
Classifier: License :: OSI Approved :: BSD License
Classifier: Operating System :: OS Independent
Requires-Python: >=3.8
License-File: LICENSE
Requires-Dist: pandas (>=1.3.0)
Requires-Dist: numpy (>=1.21.0)
Requires-Dist: gensim (>=4.0.1)
Requires-Dist: scikit-learn (>=0.24.2)
Requires-Dist: psutil (>=5.8.0)
Requires-Dist: syntok (>=1.4.4)
Requires-Dist: sentence-transformers (>=2.2.2)
Requires-Dist: transformers (>=4.24.0)
Requires-Dist: torch (>=1.13)
Requires-Dist: ray (>=2.1.0)
